LICENSE
README.md
setup.py
sidein/Sidein.py
sidein/SideinConstants.py
sidein/SideinInterface.py
sidein/_ThreadSafeSidein.py
sidein/__init__.py
sidein.egg-info/PKG-INFO
sidein.egg-info/SOURCES.txt
sidein.egg-info/dependency_links.txt
sidein.egg-info/top_level.txt
sidein/excancestors/RaisedExceptionCarrierMixin.py
sidein/excancestors/SideinExceptionCommonAncestor.py
sidein/excancestors/SideinRuntimeErrorCommonAncestor.py
sidein/excancestors/__init__.py
sidein/ns/NamespaceInterface.py
sidein/ns/_Namespace.py
sidein/ns/__init__.py
sidein/ns/_utils/DependencyDecorator.py
sidein/ns/_utils/DependencyInjector.py
sidein/ns/_utils/__init__.py
sidein/ns/exc/DependencyProviderRaisedAnExceptionError.py
sidein/ns/exc/DuplicateDependencyRequestedError.py
sidein/ns/exc/NamespaceError.py
sidein/ns/exc/NotAFunctionError.py
sidein/ns/exc/__init__.py
sidein/ns/exc/decoration/DecoratorExtractorRaisedAnExceptionError.py
sidein/ns/exc/decoration/DecoratorRaisedAnExceptionError.py
sidein/ns/exc/decoration/DependencyDecorationError.py
sidein/ns/exc/decoration/InvalidDecoratorError.py
sidein/ns/exc/decoration/InvalidDecoratorExtractorError.py
sidein/ns/exc/decoration/InvalidReplacementFunctionError.py
sidein/ns/exc/decoration/__init__.py
sidein/nsmgr/NamespaceManagerInterface.py
sidein/nsmgr/_NamespaceManager.py
sidein/nsmgr/_ThreadSafeNamespaceManager.py
sidein/nsmgr/__init__.py
sidein/nsmgr/exc/NamespaceExistsException.py
sidein/nsmgr/exc/NamespaceManagerException.py
sidein/nsmgr/exc/NamespaceNotFoundException.py
sidein/nsmgr/exc/__init__.py
sidein/obtainer/DependencyObtainerInterface.py
sidein/obtainer/_DependencyObtainer.py
sidein/obtainer/__init__.py
sidein/providers/DependencyProviderInterface.py
sidein/providers/__init__.py
sidein/providers/exc/DependencyProviderError.py
sidein/providers/exc/DependencyProviderException.py
sidein/providers/exc/__init__.py
sidein/providers/simplecontainer/GlobalSimpleContainer.py
sidein/providers/simplecontainer/SimpleContainerInterface.py
sidein/providers/simplecontainer/ThreadLocalSimpleContainer.py
