Metadata-Version: 2.1
Name: sidein
Version: 1.0.2
Summary: A flexible, object-oriented Python dependency injector
Home-page: https://github.com/vitlabuda/sidein
Author: Vít Labuda
Author-email: dev@vitlabuda.cz
License: BSD License
Project-URL: Bug Tracker, https://github.com/vitlabuda/sidein/issues
Platform: UNKNOWN
Classifier: Development Status :: 5 - Production/Stable
Classifier: Intended Audience :: Developers
Classifier: License :: OSI Approved :: BSD License
Classifier: Operating System :: OS Independent
Classifier: Programming Language :: Python :: 3
Classifier: Programming Language :: Python :: 3.9
Classifier: Programming Language :: Python :: 3.10
Classifier: Programming Language :: Python :: 3.11
Classifier: Topic :: Software Development :: Libraries
Classifier: Typing :: Typed
Requires-Python: >=3.9
License-File: LICENSE
